{
  "2025-04-07": {
    "timestamp": "2025-04-07T21:00:02.328Z",
    "status": "success"
  },
  "2025-04-11": {
    "timestamp": "2025-04-11T14:51:47.404Z",
    "status": "success"
  },
  "2025-04-12": {
    "timestamp": "2025-04-12T17:31:42.721Z",
    "status": "success"
  },
  "2025-04-13": {
    "timestamp": "2025-04-13T13:36:08.471Z",
    "status": "success"
  },
  "2025-04-14": {
    "timestamp": "2025-04-14T16:26:36.997Z",
    "status": "success"
  },
  "2025-04-16": {
    "timestamp": "2025-04-16T17:15:56.075Z",
    "status": "success"
  }
}